[
  {
    "full_name": "vercel/ms",
    "stargazers_count": 3596,
    "open_issues_count": 19,
    "forks_count": 217
  },
  {
    "full_name": "stackgl/shader-school",
    "stargazers_count": 2997,
    "open_issues_count": 48,
    "forks_count": 227
  },
  {
    "full_name": "liabru/matter-js",
    "stargazers_count": 12006,
    "open_issues_count": 194,
    "forks_count": 1569
  },
  {
    "full_name": "prisma/docs",
    "stargazers_count": 294,
    "open_issues_count": 362,
    "forks_count": 310
  },
  {
    "full_name": "jwasham/coding-interview-university",
    "stargazers_count": 190667,
    "open_issues_count": 43,
    "forks_count": 51328
  },
  {
    "full_name": "ManimCommunity/manim",
    "stargazers_count": 6678,
    "open_issues_count": 235,
    "forks_count": 548
  },
  {
    "full_name": "mirumee/saleor",
    "stargazers_count": 13940,
    "open_issues_count": 222,
    "forks_count": 3988
  },
  {
    "full_name": "snowpackjs/astro",
    "stargazers_count": 6436,
    "open_issues_count": 183,
    "forks_count": 259
  },
  {
    "full_name": "google/eleventy-high-performance-blog",
    "stargazers_count": 3397,
    "open_issues_count": 5,
    "forks_count": 214
  },
  {
    "full_name": "prisma/prisma",
    "stargazers_count": 15807,
    "open_issues_count": 1357,
    "forks_count": 559
  },
  {
    "full_name": "nocodb/nocodb",
    "stargazers_count": 17023,
    "open_issues_count": 86,
    "forks_count": 930
  },
  {
    "full_name": "substack/stream-handbook",
    "stargazers_count": 13721,
    "open_issues_count": 69,
    "forks_count": 1037
  },
  {
    "full_name": "anuraghazra/github-readme-stats",
    "stargazers_count": 29754,
    "open_issues_count": 173,
    "forks_count": 6511
  },
  {
    "full_name": "lukasoppermann/design-tokens",
    "stargazers_count": 261,
    "open_issues_count": 8,
    "forks_count": 19
  },
  {
    "full_name": "Qix-/color-convert",
    "stargazers_count": 572,
    "open_issues_count": 8,
    "forks_count": 90
  },
  {
    "full_name": "WebReflection/flatted",
    "stargazers_count": 726,
    "open_issues_count": 0,
    "forks_count": 36
  },
  {
    "full_name": "vitejs/vite",
    "stargazers_count": 30935,
    "open_issues_count": 511,
    "forks_count": 2064
  },
  {
    "full_name": "mikbry/awesome-webgpu",
    "stargazers_count": 283,
    "open_issues_count": 1,
    "forks_count": 2
  },
  {
    "full_name": "johnlindquist/kit",
    "stargazers_count": 848,
    "open_issues_count": 5,
    "forks_count": 21
  },
  {
    "full_name": "shelljs/shelljs",
    "stargazers_count": 12659,
    "open_issues_count": 94,
    "forks_count": 687
  },
  {
    "full_name": "garmeeh/next-seo",
    "stargazers_count": 3603,
    "open_issues_count": 52,
    "forks_count": 180
  },
  {
    "full_name": "i18next/react-i18next",
    "stargazers_count": 6679,
    "open_issues_count": 5,
    "forks_count": 850
  },
  {
    "full_name": "Hacker0x01/react-datepicker",
    "stargazers_count": 5981,
    "open_issues_count": 170,
    "forks_count": 1778
  },
  {
    "full_name": "sdras/career-ladders",
    "stargazers_count": 547,
    "open_issues_count": 2,
    "forks_count": 38
  },
  {
    "full_name": "natemoo-re/microsite",
    "stargazers_count": 814,
    "open_issues_count": 20,
    "forks_count": 16
  },
  {
    "full_name": "AssemblyScript/assemblyscript",
    "stargazers_count": 12553,
    "open_issues_count": 172,
    "forks_count": 514
  },
  {
    "full_name": "matthiaaas/framer-motion-hooks",
    "stargazers_count": 152,
    "open_issues_count": 0,
    "forks_count": 5
  },
  {
    "full_name": "bartdegoede/python-searchengine",
    "stargazers_count": 243,
    "open_issues_count": 0,
    "forks_count": 46
  },
  {
    "full_name": "mds/sa",
    "stargazers_count": 210,
    "open_issues_count": 0,
    "forks_count": 25
  },
  {
    "full_name": "react-hook-form/react-hook-form",
    "stargazers_count": 22836,
    "open_issues_count": 9,
    "forks_count": 1068
  }
]